clcache/__init__.py
clcache/__main__.py
clcache/monkey.py
clcache/storage.py
clcache/server/__init__.py
clcache/server/__main__.py
clcache_alt-4.2.2.data/data/clcache.pth
clcache_alt-4.2.2.dist-info/LICENSE
clcache_alt-4.2.2.dist-info/METADATA
clcache_alt-4.2.2.dist-info/WHEEL
clcache_alt-4.2.2.dist-info/entry_points.txt
clcache_alt-4.2.2.dist-info/top_level.txt
clcache_alt-4.2.2.dist-info/RECORD
